MEEGbuddy/MBComparator.py
MEEGbuddy/MEEGbuddy.py
MEEGbuddy/TMS_EEG_GUI.py
MEEGbuddy/__init__.py
MEEGbuddy/bv2fif.py
MEEGbuddy/gif_combine.py
MEEGbuddy/io.py
MEEGbuddy/meeg.py
MEEGbuddy/montage.py
MEEGbuddy/pci.py
MEEGbuddy/psd_multitaper_plot_tools.py
MEEGbuddy/read_dig_monatage.py
MEEGbuddy/set_up_source_space.py
MEEGbuddy/tests.py
MEEGbuddy/transfer_MRI.py
MEEGbuddy/transfer_behavior.py
MEEGbuddy/transfer_meeg.py
MEEGbuddy-0.0.dist-info/LICENSE
MEEGbuddy-0.0.dist-info/METADATA
MEEGbuddy-0.0.dist-info/WHEEL
MEEGbuddy-0.0.dist-info/top_level.txt
MEEGbuddy-0.0.dist-info/RECORD
