Metadata-Version: 1.2
Name: MEEGbuddy
Version: 0.0
Summary: Workflow objects for MEG (not yet) and EEG data processing
Home-page: UNKNOWN
Maintainer: Alex Rockhill
Maintainer-email: arockhill@harvard.mgh.edu
License: UNKNOWN
Download-URL: https://github.com/mghneurotherapeutics/meeg_resources.git
Platform: any
Classifier: Intended Audience :: Science/Research
Classifier: Intended Audience :: Developers
Classifier: Programming Language :: Python
Classifier: Topic :: Software Development
Classifier: Topic :: Scientific/Engineering
Classifier: Operating System :: Microsoft :: Windows
Classifier: Operating System :: POSIX
Classifier: Operating System :: Unix
Classifier: Operating System :: MacOS
